tumbleweed/__init__.py
tumbleweed/requirements.txt
tumbleweed/static/tumbleweed.css
tumbleweed/static/tumbleweed.js
tumbleweed/templates/index.html
tumbleweed/templates/nav.html
tumbleweed-1.0.5.dist-info/METADATA
tumbleweed-1.0.5.dist-info/WHEEL
tumbleweed-1.0.5.dist-info/licenses/LICENSE
tumbleweed-1.0.5.dist-info/RECORD
