Metadata-Version: 2.1
Name: tumbleweed
Version: 1.0.5
Summary: A lightweight, easy-to-setup blog framework built on Flask
Project-URL: Homepage, https://github.com/emilkovacev/tumbleweed
Author-email: Emil Kovacev <emilkovacev@gmail.com>
License: BSD 3-Clause License
Classifier: License :: OSI Approved :: BSD License
Classifier: Operating System :: OS Independent
Classifier: Programming Language :: Python :: 3
Requires-Python: >=3.7
Requires-Dist: flask
